jy/__init__.py
jy/bridge.py
jy/js_parse.py
jy/ts_parse.py
jy/util.py
jy/scrap/__init__.py
jy/scrap/find_and_replace_ids.py
jy/test/__init__.py
jy/test/test_bridge.py
jy/test/test_js_parse.py
jy-0.1.17.dist-info/LICENSE
jy-0.1.17.dist-info/METADATA
jy-0.1.17.dist-info/WHEEL
jy-0.1.17.dist-info/top_level.txt
jy-0.1.17.dist-info/RECORD
