Metadata-Version: 2.1
Name: jy
Version: 0.1.17
Summary: Tools to control JS from Python (jy for Js pY or Js python proxY)
Home-page: https://github.com/thorwhalen/jy
Author: Thor Whalen
License: apache-2.0
Platform: any
License-File: LICENSE
Requires-Dist: i2
Requires-Dist: dol
Requires-Dist: esprima
Requires-Dist: importlib-resources
